pylitsense/__init__.py
pylitsense/pylitsense.py
tests/__init__.py
tests/test_pylitsense.py
pylitsense-0.1.0.dist-info/LICENSE
pylitsense-0.1.0.dist-info/METADATA
pylitsense-0.1.0.dist-info/WHEEL
pylitsense-0.1.0.dist-info/top_level.txt
pylitsense-0.1.0.dist-info/RECORD
