Metadata-Version: 2.1
Name: pylitsense
Version: 0.1.0
Summary: Unofficial Python wrapper for the NCBI LitSense API
Author: Simon Smith
Author-email: simon@simonsmith.ca
License-File: LICENSE
Requires-Dist: requests
